{
  "treasuryBalance": 3000000,
  "rewardVaultBalance": 20000000,
  "usdcVaultBalance": 0,
  "stakedVaultBalance": 0,
  "rewardCap": 300000,
  "licenseLimit": 100,
  "licensePrice": 5000,
  "isPaused": false,
  "lastCrankedEpoch": 0,
  "networkStartDate": 1773335083050,
  "validators": [],
  "userStakes": [],
  "licenses": [],
  "proposals": [],
  "profiles": {
    "9Kqt28pfMVBsBvXYYnYQCT2BZyorAwzbR6dUmgQfsZYW": {
      "address": "9Kqt28pfMVBsBvXYYnYQCT2BZyorAwzbR6dUmgQfsZYW",
      "exnBalance": 25000000,
      "usdcBalance": 10000,
      "lastExnFaucetClaim": 0,
      "lastUsdcFaucetClaim": 0,
      "registeredAt": 1773335083693,
      "lastActive": 1773335083693,
      "totalTransactions": 0
    }
  },
  "lastTransaction": null
}